{
  "data_dir": "/root/autodl-tmp/Industrial_Project/fakeav_audio_full",
  "index_file": "/root/autodl-tmp/Industrial_Project/fakeav_audio_full/preprocess_index.jsonl",
  "epochs": 30,
  "batch_size": 16,
  "grad_accum_steps": 5,
  "lr": 5e-5,
  "weight_decay": 0.0001,
  "num_workers": 4,
  "target_steps": 400,
  "balanced_sampler": true,
  "class_weights": false,
  "scheduler": "cosine",
  "plateau_factor": 0.5,
  "plateau_patience": 2,
  "plateau_min_lr": 1e-6,
  "early_stop_patience": 0,
  "target_val_eer": 0.1,
  "warmup_epochs": 2,
  "max_grad_norm": 1.0,
  "mel_bins": 80,
  "train_wave_segments": 2,
  "global_augment_prob": 0.2,
  "global_freq_mask": 4,
  "global_time_mask": 20,
  "global_noise_std": 0.002,
  "real_augment_prob": 0.2,
  "real_augment_start": 3,
  "real_freq_mask": 4,
  "real_time_mask": 16,
  "real_noise_std": 0.0005,
  "real_gain_std": 0.05,
  "real_shift_pct": 0.08,
  "real_mixup_prob": 0.25,
  "real_mixup_alpha": 0.3,
  "fake_augment_prob": 0.0,
  "fake_freq_mask": 0,
  "fake_time_mask": 0,
  "fake_noise_std": 0.0,
  "val_real_copies": 6,
  "val_augment_freq_mask": 4,
  "val_augment_time_mask": 16,
  "val_augment_noise_std": 0.0005,
  "val_augment_shift_pct": 0.08,
  "val_augment_gain_std": 0.05,
  "val_augment_mixup_prob": 0.2,
  "val_augment_mixup_alpha": 0.3,
  "pseudo_fake_prob": 0.15,
  "pseudo_fake_max": 2,
  "pseudo_fake_freq_mask": 12,
  "pseudo_fake_time_mask": 48,
  "pseudo_fake_noise": 0.02,
  "pseudo_fake_start_epoch": 5,
  "pseudo_fake_ramp_epochs": 5,
  "wave_branch_mode": "all",
  "wave_segment_samples": 110000,
  "positive_class_weight": 1.1,
  "focal_loss": true,
  "focal_gamma": 2.0,
  "use_center_loss": true,
  "center_loss_weight": 0.05,
  "center_loss_start_epoch": 3,
  "center_loss_warmup_epochs": 4,
  "center_loss_lr": 0.0005,
  "real_margin_weight": 0.12,
  "real_margin_value": 0.5,
  "real_margin_start_epoch": 3,
  "real_margin_warmup_epochs": 4,
  "use_sync_fusion": true,
  "sync_checkpoint": "/root/autodl-tmp/Industrial_Project/sync_module.pt",
  "sync_vit_path": "/root/autodl-tmp/Industrial_Project/vit_model",
  "sync_target_frames": 16,
  "sync_audio_dim": 64,
  "sync_fusion_dropout": 0.2,
  "sync_transformer_heads": 8,
  "sync_temporal_layers": 3,
  "audio_backbone": "wavlm",
  "wavlm_model_name": "/root/autodl-tmp/Industrial_Project/models/wavlm-base-plus-sv/snapshots/feb593a6c23c1cc3d9510425c29b0a14d2b07b1e",
  "wavlm_dropout": 0.2,
  "wavlm_trainable": true,
  "wavlm_unfreeze_layers": 8,
  "wavlm_backbone_lr": 5e-6,
  "hf_local_files_only": true,
  "use_arcface_head": false,
  "arcface_warmup_epochs": 0,
  "arcface_scale": 30.0,
  "arcface_margin": 0.2,
  "eval_wave_segments": 4,
  "eval_augment_passes": 3,
  "eval_augment_prob": 0.3,
  "eval_freq_mask": 4,
  "eval_time_mask": 16,
  "eval_noise_std": 0.0005,
  "use_ema": true,
  "ema_decay": 0.997,
  "ema_start_epoch": 4,
  "resume_from": "wavlm_audio.pt",
  "device": "cuda",
  "verify_dataset": false,
  "save_path": "wavlm_audio.pt"
}
